Metadata-Version: 2.3
Name: openlineage-airflow
Version: 1.41.0
Summary: OpenLineage integration with Airflow
Keywords: openlineage
Author: OpenLineage
License: Apache-2.0
Classifier: Development Status :: 5 - Production/Stable
Classifier: Intended Audience :: Developers
Classifier: License :: OSI Approved :: Apache Software License
Classifier: Programming Language :: Python :: 3
Classifier: Programming Language :: Python :: 3.9
Classifier: Programming Language :: Python :: 3.10
Classifier: Programming Language :: Python :: 3.11
Classifier: Programming Language :: Python :: 3.12
Requires-Dist: attrs>=20.0
Requires-Dist: openlineage-integration-common==1.40.0
Requires-Dist: openlineage-sql==1.40.0
Requires-Dist: openlineage-python==1.40.0
Requires-Dist: apache-airflow>=2.5.2,<2.8 ; extra == 'airflow'
Requires-Dist: apache-airflow-providers-postgres>=2.0.0,<=5.4.0 ; extra == 'airflow'
Requires-Dist: apache-airflow-providers-mysql>=2.0.0,<=4.0.2 ; extra == 'airflow'
Requires-Dist: apache-airflow-providers-trino>=3.1.0,<=4.3.2 ; extra == 'airflow'
Requires-Dist: apache-airflow-providers-snowflake>=2.1.0,<=4.0.4 ; extra == 'airflow'
Requires-Dist: apache-airflow-providers-google>=5.0.0,<=8.11.0 ; extra == 'airflow'
Requires-Dist: apache-airflow-providers-amazon>=3.1.1,<=7.3.0 ; extra == 'airflow'
Requires-Dist: apache-airflow-providers-sftp>=2.1.1,<=4.2.4 ; extra == 'airflow'
Requires-Dist: apache-airflow-providers-ssh>=2.1.0,<=3.5.0 ; extra == 'airflow'
Requires-Dist: apache-airflow-providers-ftp>=3.3.0,<=3.3.1 ; extra == 'airflow'
Requires-Dist: apache-airflow-providers-dbt-cloud>=1.0.0,<=3.1.0 ; extra == 'airflow'
Requires-Dist: airflow-provider-great-expectations>=0.1.5,<=0.2.6 ; extra == 'airflow'
Requires-Dist: great-expectations>=0.15.0,<1.0.0 ; extra == 'airflow'
Requires-Dist: notebook>=6.0.0,<7.4.0 ; extra == 'airflow'
Requires-Dist: protobuf>=3.20,<3.21 ; extra == 'airflow'
Requires-Dist: aiohttp ; extra == 'dev'
Requires-Dist: pytest ; extra == 'dev'
Requires-Dist: pytest-cov ; extra == 'dev'
Requires-Dist: pytest-mock ; extra == 'dev'
Requires-Dist: mock ; extra == 'dev'
Requires-Dist: sqlalchemy ; extra == 'dev'
Requires-Dist: flask-sqlalchemy ; extra == 'dev'
Requires-Dist: snowflake-connector-python ; extra == 'dev'
Requires-Dist: mypy ; extra == 'dev'
Requires-Dist: tox ; extra == 'dev'
Requires-Dist: tox-uv ; extra == 'dev'
Requires-Dist: types-pyyaml ; extra == 'dev'
Requires-Dist: types-paramiko ; extra == 'dev'
Requires-Dist: types-python-dateutil ; extra == 'dev'
Requires-Dist: types-requests ; extra == 'dev'
Requires-Dist: pandas ; extra == 'dev'
Requires-Dist: boto3 ; extra == 'dev'
Requires-Dist: paramiko ; extra == 'dev'
Requires-Python: >=3.9
Project-URL: Homepage, https://openlineage.io/
Project-URL: Source, https://github.com/OpenLineage/OpenLineage/tree/main/integration/airflow
Provides-Extra: airflow
Provides-Extra: dev
